<?xml version="1.0" encoding="utf-8"?><results><method>tradesForFund</method><fund_ID>365-1</fund_ID><startDate>20000101</startDate><positionsList><position><stockSymbol>MSFT</stockSymbol><trade><opened>20031031</opened><closed>20031031</closed><sharesOrdered>3800.0</sharesOrdered><sharesFilled>3800.0</sharesFilled><price>26.213211</price><limit></limit><createdByCA>0</createdByCA><net>99610.2018</net><secFee>0.0</secFee><commission>190.0</commission><buyOrSell>Buy</buyOrSell><dayOrGTC>Day</dayOrGTC><ticketKey>BAD001D63FA29AFFC0A80134</ticketKey></trade><trade><opened>20031104</opened><closed>20031105</closed><sharesOrdered>1900.0</sharesOrdered><sharesFilled>1900.0</sharesFilled><price>26.0979736842</price><limit></limit><createdByCA>0</createdByCA><net>49586.15</net><secFee>2.33</secFee><commission>95.0</commission><buyOrSell>Sell</buyOrSell><dayOrGTC>Day</dayOrGTC><ticketKey>60A962E93FA8432DC0A80133</ticketKey></trade></position><position><stockSymbol>PFE</stockSymbol><trade><opened>20031031</opened><closed>20031031</closed><sharesOrdered>3100.0</sharesOrdered><sharesFilled>3100.0</sharesFilled><price>31.556516</price><limit></limit><createdByCA>0</createdByCA><net>97825.1996</net><secFee>0.0</secFee><commission>155.0</commission><buyOrSell>Buy</buyOrSell><dayOrGTC>Day</dayOrGTC><ticketKey>BAEC01D63FA29AFFC0A80134</ticketKey></trade><trade><opened>20031104</opened><closed>20031105</closed><sharesOrdered>1600.0</sharesOrdered><sharesFilled>1600.0</sharesFilled><price>31.29440625</price><limit></limit><createdByCA>0</createdByCA><net>50071.05</net><secFee>2.35</secFee><commission>80.0</commission><buyOrSell>Sell</buyOrSell><dayOrGTC>Day</dayOrGTC><ticketKey>60B162E93FA8432DC0A80133</ticketKey></trade></position><position><stockSymbol>SWY</stockSymbol><trade><opened>20031031</opened><closed>20031031</closed><sharesOrdered>4700.0</sharesOrdered><sharesFilled>4700.0</sharesFilled><price>21.16183</price><limit></limit><createdByCA>0</createdByCA><net>99460.601</net><secFee>0.0</secFee><commission>235.0</commission><buyOrSell>Buy</buyOrSell><dayOrGTC>Day</dayOrGTC><ticketKey>BAE001D63FA29AFFC0A80134</ticketKey></trade><trade><opened>20031104</opened><closed>20031105</closed><sharesOrdered>2300.0</sharesOrdered><sharesFilled>2300.0</sharesFilled><price>19.5324736087</price><limit></limit><createdByCA>0</createdByCA><net>44924.6893</net><secFee>2.11</secFee><commission>115.0</commission><buyOrSell>Sell</buyOrSell><dayOrGTC>Day</dayOrGTC><ticketKey>60B562E93FA8432DC0A80133</ticketKey></trade><trade><opened>20031105</opened><closed>20031105</closed><sharesOrdered>2400.0</sharesOrdered><sharesFilled>2400.0</sharesFilled><price>19.704908</price><limit></limit><createdByCA>0</createdByCA><net>47291.7792</net><secFee>2.22</secFee><commission>120.0</commission><buyOrSell>Sell</buyOrSell><dayOrGTC>Day</dayOrGTC><ticketKey>39B21D803FA91698C0A80134</ticketKey></trade></position><position><stockSymbol>DELL</stockSymbol><trade><opened>20031031</opened><closed>20031031</closed><sharesOrdered>2700.0</sharesOrdered><sharesFilled>2700.0</sharesFilled><price>36.112822</price><limit></limit><createdByCA>0</createdByCA><net>97504.6194</net><secFee>0.0</secFee><commission>135.0</commission><buyOrSell>Buy</buyOrSell><dayOrGTC>Day</dayOrGTC><ticketKey>BAF001D63FA29AFFC0A80134</ticketKey></trade><trade><opened>20031104</opened><closed>20031105</closed><sharesOrdered>1400.0</sharesOrdered><sharesFilled>1400.0</sharesFilled><price>36.0236781429</price><limit></limit><createdByCA>0</createdByCA><net>50433.1494</net><secFee>2.37</secFee><commission>70.0</commission><buyOrSell>Sell</buyOrSell><dayOrGTC>Day</dayOrGTC><ticketKey>609962E93FA8432DC0A80133</ticketKey></trade><trade><opened>20131030</opened><closed>20131030</closed><sharesOrdered>1300.0</sharesOrdered><sharesFilled>1300.0</sharesFilled><price>0.0</price><limit>0.0</limit><createdByCA>1</createdByCA><net>0.0</net><secFee>0.0</secFee><commission>0.0</commission><buyOrSell>Sell</buyOrSell><dayOrGTC>Day</dayOrGTC><ticketKey>C33F38675283EBD3C0A80146</ticketKey></trade></position><position><stockSymbol>PCS</stockSymbol><trade><opened>20031031</opened><closed>20031031</closed><sharesOrdered>22600.0</sharesOrdered><sharesFilled>22600.0</sharesFilled><price>4.479496</price><limit></limit><createdByCA>0</createdByCA><net>101236.6096</net><secFee>0.0</secFee><commission>1130.0</commission><buyOrSell>Buy</buyOrSell><dayOrGTC>Day</dayOrGTC><ticketKey>BAF401D63FA29AFFC0A80134</ticketKey></trade><trade><opened>20031104</opened><closed>20031105</closed><sharesOrdered>11300.0</sharesOrdered><sharesFilled>11300.0</sharesFilled><price>4.33979380531</price><limit></limit><createdByCA>0</createdByCA><net>49039.67</net><secFee>2.33</secFee><commission>565.0</commission><buyOrSell>Sell</buyOrSell><dayOrGTC>Day</dayOrGTC><ticketKey>60AD62E93FA8432DC0A80133</ticketKey></trade><trade><opened>20040423</opened><closed>20040423</closed><sharesOrdered>11300.0</sharesOrdered><sharesFilled>11300.0</sharesFilled><price>0.0</price><limit>0.0</limit><createdByCA>1</createdByCA><net>0.0</net><secFee>0.0</secFee><commission>0.0</commission><buyOrSell>Sell</buyOrSell><dayOrGTC>Day</dayOrGTC><ticketKey>6C0937404092142AC0A80146</ticketKey></trade></position><position><stockSymbol>G</stockSymbol><trade><opened>20031031</opened><closed>20031031</closed><sharesOrdered>3100.0</sharesOrdered><sharesFilled>3100.0</sharesFilled><price>31.866774</price><limit></limit><createdByCA>0</createdByCA><net>98786.9994</net><secFee>0.0</secFee><commission>155.0</commission><buyOrSell>Buy</buyOrSell><dayOrGTC>Day</dayOrGTC><ticketKey>BAD801D63FA29AFFC0A80134</ticketKey></trade><trade><opened>20031104</opened><closed>20031105</closed><sharesOrdered>1700.0</sharesOrdered><sharesFilled>1700.0</sharesFilled><price>33.9984058824</price><limit></limit><createdByCA>0</createdByCA><net>57797.29</net><secFee>2.71</secFee><commission>85.0</commission><buyOrSell>Sell</buyOrSell><dayOrGTC>Day</dayOrGTC><ticketKey>609D62E93FA8432DC0A80133</ticketKey></trade><trade><opened>20051003</opened><closed>20051003</closed><sharesOrdered>1400.0</sharesOrdered><sharesFilled>1400.0</sharesFilled><price>0.0</price><limit>0.0</limit><createdByCA>1</createdByCA><net>0.0</net><secFee>0.0</secFee><commission>0.0</commission><buyOrSell>Sell</buyOrSell><dayOrGTC>Day</dayOrGTC><ticketKey>9760542D4341ECCCC0A80146</ticketKey></trade></position><position><stockSymbol>LUV</stockSymbol><trade><opened>20031031</opened><closed>20031031</closed><sharesOrdered>5100.0</sharesOrdered><sharesFilled>5100.0</sharesFilled><price>19.457647</price><limit></limit><createdByCA>0</createdByCA><net>99233.9997</net><secFee>0.0</secFee><commission>255.0</commission><buyOrSell>Buy</buyOrSell><dayOrGTC>Day</dayOrGTC><ticketKey>BAD401D63FA29AFFC0A80134</ticketKey></trade><trade><opened>20031104</opened><closed>20031105</closed><sharesOrdered>2500.0</sharesOrdered><sharesFilled>2500.0</sharesFilled><price>18.449132</price><limit></limit><createdByCA>0</createdByCA><net>46122.83</net><secFee>2.17</secFee><commission>125.0</commission><buyOrSell>Sell</buyOrSell><dayOrGTC>Day</dayOrGTC><ticketKey>60A562E93FA8432DC0A80133</ticketKey></trade></position><position><stockSymbol>TM</stockSymbol><trade><opened>20031031</opened><closed>20031031</closed><sharesOrdered>1700.0</sharesOrdered><sharesFilled>1700.0</sharesFilled><price>58.218941</price><limit></limit><createdByCA>0</createdByCA><net>98972.1997</net><secFee>0.0</secFee><commission>85.0</commission><buyOrSell>Buy</buyOrSell><dayOrGTC>Day</dayOrGTC><ticketKey>BAE401D63FA29AFFC0A80134</ticketKey></trade><trade><opened>20031104</opened><closed>20031105</closed><sharesOrdered>900.0</sharesOrdered><sharesFilled>900.0</sharesFilled><price>62.9470444444</price><limit></limit><createdByCA>0</createdByCA><net>56652.34</net><secFee>2.66</secFee><commission>45.0</commission><buyOrSell>Sell</buyOrSell><dayOrGTC>Day</dayOrGTC><ticketKey>60B962E93FA8432DC0A80133</ticketKey></trade></position><position><stockSymbol>GUCG</stockSymbol><trade><opened>20031031</opened><closed>20031031</closed><sharesOrdered>1100.0</sharesOrdered><sharesFilled>1100.0</sharesFilled><price>86.175636</price><limit></limit><createdByCA>0</createdByCA><net>94793.1996</net><secFee>0.0</secFee><commission>55.0</commission><buyOrSell>Buy</buyOrSell><dayOrGTC>Day</dayOrGTC><ticketKey>BAE801D63FA29AFFC0A80134</ticketKey></trade><trade><opened>20031104</opened><closed>20031105</closed><sharesOrdered>600.0</sharesOrdered><sharesFilled>600.0</sharesFilled><price>84.4460333333</price><limit></limit><createdByCA>0</createdByCA><net>50667.62</net><secFee>2.38</secFee><commission>30.0</commission><buyOrSell>Sell</buyOrSell><dayOrGTC>Day</dayOrGTC><ticketKey>60A162E93FA8432DC0A80133</ticketKey></trade><trade><opened>20040429</opened><closed>20040429</closed><sharesOrdered>500.0</sharesOrdered><sharesFilled>500.0</sharesFilled><price>0.0</price><limit>0.0</limit><createdByCA>1</createdByCA><net>0.0</net><secFee>0.0</secFee><commission>0.0</commission><buyOrSell>Sell</buyOrSell><dayOrGTC>Day</dayOrGTC><ticketKey>280F5CA340A2F789C0A80146</ticketKey></trade></position><position><stockSymbol>OUBSF</stockSymbol><trade><opened>20031031</opened><closed>20031031</closed><sharesOrdered>1600.0</sharesOrdered><sharesFilled>1600.0</sharesFilled><price>61.421375</price><limit></limit><createdByCA>0</createdByCA><net>98274.2</net><secFee>0.0</secFee><commission>80.0</commission><buyOrSell>Buy</buyOrSell><dayOrGTC>Day</dayOrGTC><ticketKey>BADC01D63FA29AFFC0A80134</ticketKey></trade><trade><opened>20031104</opened><closed>20031105</closed><sharesOrdered>800.0</sharesOrdered><sharesFilled>800.0</sharesFilled><price>59.2972125</price><limit></limit><createdByCA>0</createdByCA><net>47437.77</net><secFee>2.23</secFee><commission>40.0</commission><buyOrSell>Sell</buyOrSell><dayOrGTC>Day</dayOrGTC><ticketKey>60BD62E93FA8432DC0A80133</ticketKey></trade><trade><opened>20060710</opened><closed>20060710</closed><sharesOrdered>1600.0</sharesOrdered><sharesFilled>1600.0</sharesFilled><price>0.0</price><limit>0.0</limit><createdByCA>1</createdByCA><net>0.0</net><secFee>0.0</secFee><commission>0.0</commission><buyOrSell>Buy</buyOrSell><dayOrGTC>Day</dayOrGTC><ticketKey>419425DF44B30DC4C0A80146</ticketKey></trade><trade><opened>20060710</opened><closed>20060710</closed><sharesOrdered>800.0</sharesOrdered><sharesFilled>800.0</sharesFilled><price>0.0</price><limit>0.0</limit><createdByCA>1</createdByCA><net>0.0</net><secFee>0.0</secFee><commission>0.0</commission><buyOrSell>Sell</buyOrSell><dayOrGTC>Day</dayOrGTC><ticketKey>418F25DF44B30DC4C0A80146</ticketKey></trade><trade><opened>20080519</opened><closed>20080519</closed><sharesOrdered>80.0</sharesOrdered><sharesFilled>80.0</sharesFilled><price>0.0</price><limit>0.0</limit><createdByCA>1</createdByCA><net>0.0</net><secFee>0.0</secFee><commission>0.0</commission><buyOrSell>Buy</buyOrSell><dayOrGTC>Day</dayOrGTC><ticketKey>149C1A0A48323220C0A80146</ticketKey></trade></position><position><stockSymbol>WMT</stockSymbol><trade><opened>20031105</opened><closed>20031105</closed><sharesOrdered>800.0</sharesOrdered><sharesFilled>800.0</sharesFilled><price>58.34</price><limit></limit><createdByCA>0</createdByCA><net>46672.0</net><secFee>0.0</secFee><commission>40.0</commission><buyOrSell>Buy</buyOrSell><dayOrGTC>Day</dayOrGTC><ticketKey>15E71D803FA9102DC0A80134</ticketKey></trade></position><position><stockSymbol>BAC</stockSymbol><trade><opened>20031105</opened><closed>20031105</closed><sharesOrdered>600.0</sharesOrdered><sharesFilled>600.0</sharesFilled><price>75.843667</price><limit></limit><createdByCA>0</createdByCA><net>45506.2002</net><secFee>0.0</secFee><commission>30.0</commission><buyOrSell>Buy</buyOrSell><dayOrGTC>Day</dayOrGTC><ticketKey>15EB1D803FA9102DC0A80134</ticketKey></trade><trade><opened>20040830</opened><closed>20040830</closed><sharesOrdered>600.0</sharesOrdered><sharesFilled>600.0</sharesFilled><price>0.0</price><limit>0.0</limit><createdByCA>1</createdByCA><net>0.0</net><secFee>0.0</secFee><commission>0.0</commission><buyOrSell>Sell</buyOrSell><dayOrGTC>Day</dayOrGTC><ticketKey>4FD805B84133DE05C0A80146</ticketKey></trade><trade><opened>20040830</opened><closed>20040830</closed><sharesOrdered>1200.0</sharesOrdered><sharesFilled>1200.0</sharesFilled><price>0.0</price><limit>0.0</limit><createdByCA>1</createdByCA><net>0.0</net><secFee>0.0</secFee><commission>0.0</commission><buyOrSell>Buy</buyOrSell><dayOrGTC>Day</dayOrGTC><ticketKey>4FDD05B84133DE05C0A80146</ticketKey></trade></position><position><stockSymbol>GE</stockSymbol><trade><opened>20031105</opened><closed>20031105</closed><sharesOrdered>1600.0</sharesOrdered><sharesFilled>1600.0</sharesFilled><price>28.56125</price><limit></limit><createdByCA>0</createdByCA><net>45698.0</net><secFee>0.0</secFee><commission>80.0</commission><buyOrSell>Buy</buyOrSell><dayOrGTC>Day</dayOrGTC><ticketKey>15E31D803FA9102DC0A80134</ticketKey></trade></position><position><stockSymbol>HON</stockSymbol><trade><opened>20031105</opened><closed>20031105</closed><sharesOrdered>1500.0</sharesOrdered><sharesFilled>1500.0</sharesFilled><price>30.800133</price><limit></limit><createdByCA>0</createdByCA><net>46200.1995</net><secFee>0.0</secFee><commission>75.0</commission><buyOrSell>Buy</buyOrSell><dayOrGTC>Day</dayOrGTC><ticketKey>307C1D803FA913E1C0A80134</ticketKey></trade></position><position><stockSymbol>JNJ</stockSymbol><trade><opened>20031105</opened><closed>20031105</closed><sharesOrdered>900.0</sharesOrdered><sharesFilled>900.0</sharesFilled><price>49.310222</price><limit></limit><createdByCA>0</createdByCA><net>44379.1998</net><secFee>0.0</secFee><commission>45.0</commission><buyOrSell>Buy</buyOrSell><dayOrGTC>Day</dayOrGTC><ticketKey>33B71D803FA914C0C0A80134</ticketKey></trade></position><position><stockSymbol>HMC</stockSymbol><trade><opened>20031105</opened><closed>20031105</closed><sharesOrdered>2200.0</sharesOrdered><sharesFilled>2200.0</sharesFilled><price>20.790182</price><limit></limit><createdByCA>0</createdByCA><net>45738.4004</net><secFee>0.0</secFee><commission>110.0</commission><buyOrSell>Buy</buyOrSell><dayOrGTC>Day</dayOrGTC><ticketKey>16131D803FA910F1C0A80134</ticketKey></trade></position><position><stockSymbol>S</stockSymbol><trade><opened>20040423</opened><closed>20040423</closed><sharesOrdered>5650.0</sharesOrdered><sharesFilled>5650.0</sharesFilled><price>0.0</price><limit>0.0</limit><createdByCA>1</createdByCA><net>0.0</net><secFee>0.0</secFee><commission>0.0</commission><buyOrSell>Buy</buyOrSell><dayOrGTC>Day</dayOrGTC><ticketKey>FBEE37404092122AC0A80146</ticketKey></trade></position><position><stockSymbol>PG</stockSymbol><trade><opened>20051003</opened><closed>20051003</closed><sharesOrdered>1365.0</sharesOrdered><sharesFilled>1365.0</sharesFilled><price>0.0</price><limit>0.0</limit><createdByCA>1</createdByCA><net>0.0</net><secFee>0.0</secFee><commission>0.0</commission><buyOrSell>Buy</buyOrSell><dayOrGTC>Day</dayOrGTC><ticketKey>71D9542D4341EB7CC0A80146</ticketKey></trade></position><position><stockSymbol>EQ</stockSymbol><trade><opened>20060517</opened><closed>20060517</closed><sharesOrdered>282.0</sharesOrdered><sharesFilled>282.0</sharesFilled><price>0.0</price><limit>0.0</limit><createdByCA>1</createdByCA><net>0.0</net><secFee>0.0</secFee><commission>0.0</commission><buyOrSell>Buy</buyOrSell><dayOrGTC>Day</dayOrGTC><ticketKey>83B143F0446D2E07C0A80146</ticketKey></trade><trade><opened>20090701</opened><closed>20090701</closed><sharesOrdered>282.0</sharesOrdered><sharesFilled>282.0</sharesFilled><price>0.0</price><limit>0.0</limit><createdByCA>1</createdByCA><net>0.0</net><secFee>0.0</secFee><commission>0.0</commission><buyOrSell>Sell</buyOrSell><dayOrGTC>Day</dayOrGTC><ticketKey>1E4D200D4A4C18EFC0A80146</ticketKey></trade></position><position><stockSymbol>CTL</stockSymbol><trade><opened>20090701</opened><closed>20090701</closed><sharesOrdered>386.0</sharesOrdered><sharesFilled>386.0</sharesFilled><price>0.0</price><limit>0.0</limit><createdByCA>1</createdByCA><net>0.0</net><secFee>0.0</secFee><commission>0.0</commission><buyOrSell>Buy</buyOrSell><dayOrGTC>Day</dayOrGTC><ticketKey>3579200D4A4C1734C0A80146</ticketKey></trade></position></positionsList></results>