<?xml version="1.0" encoding="utf-8"?><results><method>positionDetail</method><date>20150417</date><positionsList><position><stockSymbol>PFE</stockSymbol><name>PFIZER INC</name><shares>2000</shares><dividends>0.0</dividends><value>70080.0</value><ratio>0.0382567791711</ratio><price>35.04</price></position><position><stockSymbol>BMY</stockSymbol><name>BRISTOL-MYERS SQUIBB</name><shares>2000</shares><dividends>0.0</dividends><value>130700.0</value><ratio>0.0713493298753</ratio><price>65.35</price></position><position><stockSymbol>MRK</stockSymbol><name>MERCK &amp; CO</name><shares>2000</shares><dividends>0.0</dividends><value>113760.0</value><ratio>0.0621017579695</ratio><price>56.88</price></position><position><stockSymbol>LLY</stockSymbol><name>LILLY (ELI)</name><shares>1000</shares><dividends>0.0</dividends><value>72470.0</value><ratio>0.039561483826</ratio><price>72.47</price></position><position><stockSymbol>CCE</stockSymbol><name>COCA-COLA ENTERPRISES</name><shares>2000</shares><dividends>0.0</dividends><value>90180.0</value><ratio>0.0492293999093</ratio><price>45.09</price></position><position><stockSymbol>KO</stockSymbol><name>COCA-COLA CO</name><shares>4000</shares><dividends>0.0</dividends><value>161200.0</value><ratio>0.0879993265179</ratio><price>40.3</price></position><position><stockSymbol>VZ</stockSymbol><name>Verizon</name><shares>2000</shares><dividends>0.0</dividends><value>97800.0</value><ratio>0.0533891695624</ratio><price>48.9</price></position><position><stockSymbol>INTC</stockSymbol><name>INTEL CORP</name><shares>2500</shares><dividends>0.0</dividends><value>81175.0</value><ratio>0.0443135566383</ratio><price>32.47</price></position><position><stockSymbol>MMC</stockSymbol><name>MARSH &amp; MCLENNAN COS INC</name><shares>1000</shares><dividends>0.0</dividends><value>56190.0</value><ratio>0.0306742069295</ratio><price>56.19</price></position><position><stockSymbol>T</stockSymbol><name>AT&amp;T Inc</name><shares>3558</shares><dividends>0.0</dividends><value>115670.58</value><ratio>0.0631447465133</ratio><price>32.51</price></position><position><stockSymbol>GE</stockSymbol><name>GENERAL ELECTRIC</name><shares>2000</shares><dividends>0.0</dividends><value>54500.0</value><ratio>0.0297516333451</ratio><price>27.25</price></position><position><stockSymbol>CSCO</stockSymbol><name>CISCO SYSTEMS</name><shares>1500</shares><dividends>0.0</dividends><value>41880.0</value><ratio>0.0228623560457</ratio><price>27.92</price></position><position><stockSymbol>IDARQ</stockSymbol><name>Idearc Inc</name><shares>120</shares><dividends>0.0</dividends><value>0.0</value><ratio>0.0</ratio><price></price></position><position><stockSymbol>C</stockSymbol><name>CITIGROUP INC</name><shares>1000</shares><dividends>0.0</dividends><value>53070.0</value><ratio>0.0289709941582</ratio><price>53.07</price></position><position><stockSymbol>BAC</stockSymbol><name>BANK OF AMERICA CORP</name><shares>2000</shares><dividends>0.0</dividends><value>31120.0</value><ratio>0.0169884555908</ratio><price>15.56</price></position><position><stockSymbol>KEY</stockSymbol><name>KEYCORP</name><shares>1000</shares><dividends>0.0</dividends><value>14090.0</value><ratio>0.00769175254738</ratio><price>14.09</price></position><position><stockSymbol>STI</stockSymbol><name>SUNTRUST BANKS</name><shares>500</shares><dividends>0.0</dividends><value>20705.0</value><ratio>0.0113028911635</ratio><price>41.41</price></position><position><stockSymbol>CTL</stockSymbol><name>CenturyLink Inc</name><shares>2000</shares><dividends>0.0</dividends><value>69360.0</value><ratio>0.03786373007</ratio><price>34.68</price></position><position><stockSymbol>KMI</stockSymbol><name>Kinder Morgan Inc</name><shares>1000</shares><dividends>0.0</dividends><value>43900.0</value><ratio>0.0239650771348</ratio><price>43.9</price></position><position><stockSymbol>XEL</stockSymbol><name>XCEL ENERGY INC</name><shares>1000</shares><dividends>0.0</dividends><value>34370.0</value><ratio>0.0187626355609</ratio><price>34.37</price></position><position><stockSymbol>PCL</stockSymbol><name>PLUM CREEK TIMBER L.P.</name><shares>1000</shares><dividends>0.0</dividends><value>42270.0</value><ratio>0.0230752576421</ratio><price>42.27</price></position><position><stockSymbol>SO</stockSymbol><name>SOUTHERN CO</name><shares>1500</shares><dividends>0.0</dividends><value>66165.0</value><ratio>0.036119574684</ratio><price>44.11</price></position><position><stockSymbol>WIN</stockSymbol><name>Windstream Holdings Inc</name><shares>5000</shares><dividends>0.0</dividends><value>38450.0</value><ratio>0.0209899138003</ratio><price>7.69</price></position><position><stockSymbol>FE</stockSymbol><name>FIRSTENERGY CORP</name><shares>1000</shares><dividends>0.0</dividends><value>35070.0</value><ratio>0.0191447666314</ratio><price>35.07</price></position><position><stockSymbol>FTR</stockSymbol><name>Frontier Communications Corp</name><shares>3000</shares><dividends>0.0</dividends><value>21060.0</value><ratio>0.0114966862064</ratio><price>7.02</price></position><position><stockSymbol>RIG</stockSymbol><name>Transocean Ltd</name><shares>1000</shares><dividends>0.0</dividends><value>17980.0</value><ratio>0.00981530949623</ratio><price>17.98</price></position><position><stockSymbol>PCG</stockSymbol><name>PG&amp;E CORP</name><shares>1000</shares><dividends>0.0</dividends><value>52360.0</value><ratio>0.0285834040724</ratio><price>52.36</price></position><position><stockSymbol>VTR</stockSymbol><name>VENTAS INC</name><shares>700</shares><dividends>0.0</dividends><value>51037.0</value><ratio>0.0278611763492</ratio><price>72.91</price></position><position><stockSymbol>HCN</stockSymbol><name>HEALTH CARE REIT</name><shares>700</shares><dividends>0.0</dividends><value>52682.0</value><ratio>0.0287591843649</ratio><price>75.26</price></position><position><stockSymbol>LINE</stockSymbol><name>Linn Energy, LLC</name><shares>500</shares><dividends>0.0</dividends><value>6460.0</value><ratio>0.00352652387907</ratio><price>12.92</price></position><position><stockSymbol>BBEP</stockSymbol><name>BreitBurn Energy Partners L.P.</name><shares>1585</shares><dividends>66.0</dividends><value>9953.8</value><ratio>0.00543379464202</ratio><price>6.28</price></position><position><stockSymbol>NTI</stockSymbol><name>Northern Tier Energy Inc</name><shares>500</shares><dividends>0.0</dividends><value>12800.0</value><ratio>0.00698753957462</ratio><price>25.6</price></position><position><stockSymbol>AT</stockSymbol><name>Atlantic Power Corporation</name><shares>6500</shares><dividends>0.0</dividends><value>18980.0</value><ratio>0.0103612110255</ratio><price>2.92</price></position><position><stockSymbol>COP</stockSymbol><name>ConocoPhillips</name><shares>350</shares><dividends>0.0</dividends><value>23691.5</value><ratio>0.0129332260806</ratio><price>67.69</price></position><position><stockSymbol>RDS.A</stockSymbol><name>Royal Dutch Shell PLC Class A</name><shares>350</shares><dividends>0.0</dividends><value>21959.0</value><ratio>0.0119874516812</ratio><price>62.74</price></position></positionsList><fund_ID>714-1</fund_ID></results>